pureml_policy/__init__.py
pureml_policy/assignments.py
pureml_policy/frameworks.py
pureml_policy/grade.py
pureml_policy/policy.py
pureml_policy/policy_eval.py
pureml_policy/reports.py
pureml_policy/reslut_formation.py
pureml_policy/schema.py
pureml_policy/utils/routes.py
pureml_policy-0.2.4.dist-info/METADATA
pureml_policy-0.2.4.dist-info/WHEEL
pureml_policy-0.2.4.dist-info/RECORD
