Metadata-Version: 2.1
Name: pureml-policy
Version: 0.2.4
Summary: 
Author: vamsidhar muthireddy
Author-email: vamsi.muthireddy@gmail.com
Requires-Python: >=3.9,<3.13
Classifier: Programming Language :: Python :: 3
Classifier: Programming Language :: Python :: 3.9
Classifier: Programming Language :: Python :: 3.10
Classifier: Programming Language :: Python :: 3.11
Requires-Dist: PyPDF2 (>=3.0.1,<4.0.0)
Requires-Dist: daisy (>=1.0,<2.0)
Requires-Dist: fairlearn (>=0.8.0,<0.9.0)
Requires-Dist: joblib (>=1.2.0,<2.0.0)
Requires-Dist: pandas (>=2.2.0,<3.0.0)
Requires-Dist: plotly (>=5.18.0,<6.0.0)
Requires-Dist: pureml (==0.4.6)
Requires-Dist: pureml-evaluate (==0.1.6)
Requires-Dist: pydantic (>=2.5.3,<3.0.0)
Requires-Dist: reportlab (>=4.0.4,<5.0.0)
Requires-Dist: requests_toolbelt (>=1.0.0,<2.0.0)
Requires-Dist: scikit-learn (>=1.2.2,<2.0.0)
Requires-Dist: scipy (>=1.9.1,<2.0.0) ; python_version >= "3.9" and python_version < "3.12"
Requires-Dist: seaborn (>=0.12.2,<0.13.0)
Requires-Dist: structlog (>=24.1.0,<25.0.0)
